helperlib/__init__.py
helperlib/binary.py
helperlib/exception.py
helperlib/internal.py
helperlib/lazy.py
helperlib/logging.py
helperlib/minimize.py
helperlib/spinner.py
helperlib/terminal.py
helperlib-0.3.0.dist-info/DESCRIPTION.rst
helperlib-0.3.0.dist-info/METADATA
helperlib-0.3.0.dist-info/RECORD
helperlib-0.3.0.dist-info/WHEEL
helperlib-0.3.0.dist-info/metadata.json
helperlib-0.3.0.dist-info/top_level.txt
