Metadata-Version: 2.0
Name: helperlib
Version: 0.3.0
Summary: A collection of useful python modules
Home-page: https://github.com/bluec0re/python-helperlib.git
Author: bluec0re
Author-email: UNKNOWN
License: UNKNOWN
Download-URL: https://github.com/bluec0re/python-helperlib/archive/master.zip
Platform: UNKNOWN
